{
  "source": "elastic",
  "name": "First Time Seen AWS Secret Value Accessed in Secrets Manager",
  "slug": "credential_access_new_terms_secretsmanager_getsecretvalue",
  "category": "any",
  "language": "kuery",
  "risk_score": 47,
  "tags": [
    "Domain: Cloud",
    "Data Source: AWS",
    "Data Source: Amazon Web Services",
    "Data Source: AWS Secrets Manager",
    "Tactic: Credential Access",
    "Resources: Investigation Guide"
  ],
  "elastic_path": "rules/integrations/aws/credential_access_new_terms_secretsmanager_getsecretvalue.toml",
  "raw_query": "data_stream.dataset: aws.cloudtrail \n    and event.provider: secretsmanager.amazonaws.com \n    and event.action: GetSecretValue \n    and event.outcome: success\n",
  "conditions": []
}