{
  "source": "elastic",
  "name": "AWS Configuration Recorder Stopped",
  "slug": "defense_evasion_configuration_recorder_stopped",
  "category": "any",
  "language": "kuery",
  "risk_score": 73,
  "tags": [
    "Domain: Cloud",
    "Data Source: AWS",
    "Data Source: Amazon Web Services",
    "Data Source: AWS Config",
    "Tactic: Defense Evasion",
    "Resources: Investigation Guide"
  ],
  "elastic_path": "rules/integrations/aws/defense_evasion_configuration_recorder_stopped.toml",
  "raw_query": "data_stream.dataset: aws.cloudtrail \n    and event.provider: config.amazonaws.com \n    and event.action: StopConfigurationRecorder \n    and event.outcome: success\n",
  "conditions": []
}