{
  "id": "2f7cb1dd-1587-5930-9d6a-adc51d61f736",
  "catalog": "elastic",
  "name": "Kubernetes Secret or ConfigMap Access via Azure Arc Proxy",
  "description": "",
  "severity": "high",
  "mitre_techniques": [
    "attack.credential-access",
    "attack.collection"
  ],
  "event_categories": [
    "any"
  ],
  "conditions": [
    {
      "field": "kubernetes.audit.objectref.resource",
      "raw_field": "kubernetes.audit.objectRef.resource",
      "operator": "in",
      "values": [
        "secrets",
        "configmaps"
      ],
      "raw_values": [
        "secrets",
        "configmaps"
      ]
    },
    {
      "field": "kubernetes.audit.verb",
      "raw_field": "kubernetes.audit.verb",
      "operator": "in",
      "values": [
        "get",
        "list",
        "create",
        "update",
        "patch",
        "delete"
      ],
      "raw_values": [
        "get",
        "list",
        "create",
        "update",
        "patch",
        "delete"
      ]
    },
    {
      "field": "not",
      "raw_field": "NOT",
      "operator": "in",
      "values": [
        "azure-arc",
        "azure-arc-release",
        "kube-system"
      ],
      "raw_values": [
        "azure-arc",
        "azure-arc-release",
        "kube-system"
      ]
    },
    {
      "field": "arc",
      "raw_field": "arc",
      "operator": ":",
      "values": [
        ")\n    and kubernetes.audit.objectref.resource in ("
      ],
      "raw_values": [
        ")\n    AND kubernetes.audit.objectRef.resource IN ("
      ]
    }
  ],
  "raw_query": "FROM logs-kubernetes.audit_logs-* metadata _id, _version, _index\n| WHERE STARTS_WITH(kubernetes.audit.user.username, \"system:serviceaccount:azure-arc:\")\n    AND kubernetes.audit.objectRef.resource IN (\"secrets\", \"configmaps\")\n    AND kubernetes.audit.verb IN (\"get\", \"list\", \"create\", \"update\", \"patch\", \"delete\")\n    AND kubernetes.audit.objectRef.namespace NOT IN (\"azure-arc\", \"azure-arc-release\", \"kube-system\")\n    AND NOT STARTS_WITH(kubernetes.audit.objectRef.name, \"sh.helm.release.v1\")\n\n| STATS\n    Esql.verb_values = VALUES(kubernetes.audit.verb),\n    Esql.resource_type_values = VALUES(kubernetes.audit.objectRef.resource),\n    Esql.resource_name_values = VALUES(kubernetes.audit.objectRef.name),\n    Esql.namespace_values = VALUES(kubernetes.audit.objectRef.namespace),\n    Esql.acting_user_values = VALUES(kubernetes.audit.user.username),\n    Esql.user_agent_values = VALUES(kubernetes.audit.userAgent),\n    Esql.source_ips_values = VALUES(kubernetes.audit.sourceIPs),\n    Esql.response_code_values = VALUES(kubernetes.audit.responseStatus.code),\n    Esql.timestamp_first_seen = MIN(@timestamp),\n    Esql.timestamp_last_seen = MAX(@timestamp),\n    Esql.event_count = COUNT(*)\n    BY kubernetes.audit.impersonatedUser.username\n\n| WHERE Esql.timestamp_first_seen >= NOW() - 9 minutes\n| KEEP *\n",
  "language": "esql",
  "translated_query": null,
  "source_path": "rules/integrations/kubernetes/credential_access_azure_arc_proxy_secret_configmap_access.toml",
  "metadata": {
    "risk_score": 47,
    "tags": [
      "Data Source: Kubernetes",
      "Domain: Kubernetes",
      "Domain: Cloud",
      "Use Case: Threat Detection",
      "Tactic: Credential Access",
      "Tactic: Collection",
      "Resources: Investigation Guide"
    ]
  }
}