{
  "id": "5f7c67ba-d403-58ad-afcb-37f60ddbe288",
  "catalog": "elastic",
  "name": "Okta Alerts Following Unusual Proxy Authentication",
  "description": "",
  "severity": "critical",
  "mitre_techniques": [
    "attack.initial-access"
  ],
  "event_categories": [
    "any"
  ],
  "conditions": [
    {
      "field": "not",
      "raw_field": "not",
      "operator": "in",
      "values": [
        "6f1bb4b2-7dc8-11ee-92b2-f661ea17fbcd",
        "af2d8e4c-3b7c-4e91-8f5a-6c9d0e1f2a3b"
      ],
      "raw_values": [
        "6f1bb4b2-7dc8-11ee-92b2-f661ea17fbcd",
        "af2d8e4c-3b7c-4e91-8f5a-6c9d0e1f2a3b"
      ]
    },
    {
      "field": "data_stream.dataset",
      "raw_field": "data_stream.dataset",
      "operator": "==",
      "values": [
        "okta.system"
      ],
      "raw_values": [
        "okta.system"
      ]
    },
    {
      "field": "kibana.alert.rule.rule_id",
      "raw_field": "kibana.alert.rule.rule_id",
      "operator": "==",
      "values": [
        "6f1bb4b2-7dc8-11ee-92b2-f661ea17fbcd"
      ],
      "raw_values": [
        "6f1bb4b2-7dc8-11ee-92b2-f661ea17fbcd"
      ]
    },
    {
      "field": "kibana.alert.severity",
      "raw_field": "kibana.alert.severity",
      "operator": "!=",
      "values": [
        "low"
      ],
      "raw_values": [
        "low"
      ]
    }
  ],
  "raw_query": "sequence by user.name with maxspan=30m\n    [any where data_stream.dataset == \"okta.system\" and\n        kibana.alert.rule.rule_id == \"6f1bb4b2-7dc8-11ee-92b2-f661ea17fbcd\"]\n    [any where data_stream.dataset == \"okta.system\" and\n        kibana.alert.rule.rule_id != null and\n        kibana.alert.severity != \"low\" and\n        kibana.alert.rule.rule_id not in  (\n            \"6f1bb4b2-7dc8-11ee-92b2-f661ea17fbcd\",\n            \"af2d8e4c-3b7c-4e91-8f5a-6c9d0e1f2a3b\"\n        )\n    ]\n",
  "language": "eql",
  "translated_query": null,
  "source_path": "rules/integrations/okta/initial_access_okta_suspicious_activity_after_proxy_authentication.toml",
  "metadata": {
    "risk_score": 73,
    "tags": [
      "Domain: Identity",
      "Domain: Cloud",
      "Use Case: Identity and Access Audit",
      "Use Case: Threat Detection",
      "Data Source: Okta",
      "Data Source: Okta System Logs",
      "Tactic: Initial Access",
      "Rule Type: Higher-Order Rule",
      "Resources: Investigation Guide"
    ]
  }
}