{
  "id": "9c73dfc7-a76e-5718-a9ff-8d76d24dcd09",
  "catalog": "elastic",
  "name": "Threat Intel Windows Registry Indicator Match",
  "description": "",
  "severity": "critical",
  "mitre_techniques": [],
  "event_categories": [
    "any"
  ],
  "conditions": [],
  "raw_query": "registry.path:*\n",
  "language": "kuery",
  "translated_query": null,
  "source_path": "rules/threat_intel/threat_intel_indicator_match_registry.toml",
  "metadata": {
    "risk_score": 73,
    "tags": [
      "OS: Windows",
      "Data Source: Elastic Endgame",
      "Rule Type: Threat Match",
      "Resources: Investigation Guide"
    ]
  }
}